telegram_click/__init__.py
telegram_click/argument.py
telegram_click/const.py
telegram_click/decorator.py
telegram_click/error_handler.py
telegram_click/help.py
telegram_click/parser.py
telegram_click/util.py
telegram_click/permission/__init__.py
telegram_click/permission/base.py
telegram_click/permission/chat.py
telegram_click/permission/user.py
telegram_click-6.0.3.dist-info/LICENSE
telegram_click-6.0.3.dist-info/METADATA
telegram_click-6.0.3.dist-info/WHEEL
telegram_click-6.0.3.dist-info/top_level.txt
telegram_click-6.0.3.dist-info/RECORD
