Metadata-Version: 2.1
Name: telegram_click
Version: 6.0.3
Summary: Click inspired command interface toolkit for pyton-telegram-bot
Home-page: https://github.com/markusressel/telegram-click
Author: Markus Ressel
Author-email: mail@markusressel.de
License: MIT
Classifier: Development Status :: 5 - Production/Stable
Classifier: License :: OSI Approved :: MIT License
Classifier: Programming Language :: Python :: 3
Classifier: Programming Language :: Python :: 3.11
Classifier: Programming Language :: Python :: 3.12
License-File: LICENSE
Requires-Dist: anyio
Requires-Dist: certifi
Requires-Dist: emoji
Requires-Dist: h11
Requires-Dist: httpcore
Requires-Dist: httpx
Requires-Dist: idna
Requires-Dist: python-telegram-bot
Requires-Dist: sniffio
